pybpodgui_api/__init__.py
pybpodgui_api/settings.py
pybpodgui_api/com/__init__.py
pybpodgui_api/com/messaging/__init__.py
pybpodgui_api/com/messaging/parser.py
pybpodgui_api/exceptions/__init__.py
pybpodgui_api/exceptions/api_error.py
pybpodgui_api/exceptions/board_error.py
pybpodgui_api/exceptions/invalid_session.py
pybpodgui_api/exceptions/invalid_task.py
pybpodgui_api/exceptions/pycontrol_error.py
pybpodgui_api/exceptions/run_setup.py
pybpodgui_api/exceptions/wrong_subject_error.py
pybpodgui_api/models/__init__.py
pybpodgui_api/models/board/__init__.py
pybpodgui_api/models/board/board_base.py
pybpodgui_api/models/board/board_com.py
pybpodgui_api/models/board/board_io.py
pybpodgui_api/models/board/non_blockingcsvreader.py
pybpodgui_api/models/board/non_blockingstreamreader.py
pybpodgui_api/models/board/run_settings_template.py
pybpodgui_api/models/experiment/__init__.py
pybpodgui_api/models/experiment/experiment_base.py
pybpodgui_api/models/experiment/experiment_io.py
pybpodgui_api/models/project/__init__.py
pybpodgui_api/models/project/project_base.py
pybpodgui_api/models/project/project_io.py
pybpodgui_api/models/session/__init__.py
pybpodgui_api/models/session/session_base.py
pybpodgui_api/models/session/session_com.py
pybpodgui_api/models/session/session_io.py
pybpodgui_api/models/setup/__init__.py
pybpodgui_api/models/setup/board_task.py
pybpodgui_api/models/setup/setup_base.py
pybpodgui_api/models/setup/setup_com.py
pybpodgui_api/models/setup/setup_io.py
pybpodgui_api/models/setup/task_variable.py
pybpodgui_api/models/subject/__init__.py
pybpodgui_api/models/subject/subject_base.py
pybpodgui_api/models/subject/subject_com.py
pybpodgui_api/models/subject/subject_io.py
pybpodgui_api/models/task/__init__.py
pybpodgui_api/models/task/task_base.py
pybpodgui_api/models/task/task_file.py
pybpodgui_api/models/task/task_io.py
pybpodgui_api/models/task/taskcommand.py
pybpodgui_api/models/user/__init__.py
pybpodgui_api/models/user/user_base.py
pybpod_gui_api-1.8.2.dist-info/LICENSE.md
pybpod_gui_api-1.8.2.dist-info/METADATA
pybpod_gui_api-1.8.2.dist-info/WHEEL
pybpod_gui_api-1.8.2.dist-info/top_level.txt
pybpod_gui_api-1.8.2.dist-info/RECORD
