Metadata-Version: 2.1
Name: pybpod-gui-api
Version: 1.8.2
Summary: pybpod-gui-api is an API for the PyBpodGUI
Home-page: https://github.com/pybpod/pybpod-gui-api/
Author: ['Ricardo Ribeiro', 'Carlos Mão de Ferro', 'Luís Teixeira']
Author-email: ricardojvr@gmail.com, micboucinha@gmail.com
License: MIT
Platform: UNKNOWN
Requires-Dist: pybpod-api
Requires-Dist: safe-and-collaborative-architecture
Requires-Dist: pandas
